README.md
setup.py
pysbr/__init__.py
pysbr/configure.py
pysbr/constants.py
pysbr/decorators.py
pysbr.egg-info/PKG-INFO
pysbr.egg-info/SOURCES.txt
pysbr.egg-info/dependency_links.txt
pysbr.egg-info/requires.txt
pysbr.egg-info/top_level.txt