Metadata-Version: 1.1
Name: pysbr
Version: 0.0.1
Summary: Decorators for provisioning tests with remote webdrivers.
Home-page: https://neetjn.github.io/py-selenium-browser
Author: John Nolette
Author-email: john@neetgroup.net
License: MIT
Platform: UNKNOWN
Classifier: Development Status :: 4 - Beta
Classifier: Intended Audience :: Developers
Classifier: License :: OSI Approved :: Apache Software License
Classifier: Programming Language :: Python :: 2.7
Classifier: Programming Language :: Python :: 3.6
